Blauwal3_Associate-1.3.0-py3.10-nspkg.pth
orangecontrib/associate/__init__.py
orangecontrib/associate/_fpgrowth.cp310-win_amd64.pyd
orangecontrib/associate/_fpgrowth.cpp
orangecontrib/associate/_fpgrowth.pyx
orangecontrib/associate/fpgrowth.py
orangecontrib/associate/i18n_config.py
orangecontrib/associate/locale/associate.de.yml
orangecontrib/associate/locale/associate.en.yml
orangecontrib/associate/locale/associate.zh.yml
orangecontrib/associate/widgets/__init__.py
orangecontrib/associate/widgets/owassociate.py
orangecontrib/associate/widgets/owitemsets.py
orangecontrib/associate/widgets/icons/AssociationRules.svg
orangecontrib/associate/widgets/icons/FrequentItemsets.svg
orangecontrib/associate/widgets/tests/__init__.py
orangecontrib/associate/widgets/tests/test_owassociate.py
orangecontrib/associate/widgets/tests/data/market-basket.tab
orangecontrib/associate/widgets/tests/data/test_owitemsets.py
Blauwal3_Associate-1.3.0.dist-info/LICENSE
Blauwal3_Associate-1.3.0.dist-info/METADATA
Blauwal3_Associate-1.3.0.dist-info/WHEEL
Blauwal3_Associate-1.3.0.dist-info/entry_points.txt
Blauwal3_Associate-1.3.0.dist-info/namespace_packages.txt
Blauwal3_Associate-1.3.0.dist-info/top_level.txt
Blauwal3_Associate-1.3.0.dist-info/RECORD
