Metadata-Version: 2.1
Name: Blauwal3-Associate
Version: 1.3.0
Summary: 用于挖掘频繁项集和关联规则的蓝鲸插件
Home-page: https://github.com/biolab/orange3-associate
Author: 大圣实验楼
Author-email: dashenglab@163.com
Keywords: frequent itemset mining,frequent pattern mining,association rules,apriori,fp-growth,frequent patterns,FIM,FPM,orange3 add-on
Classifier: Programming Language :: Python
Classifier: License :: OSI Approved :: GNU General Public License v3 or later (GPLv3+)
Classifier: Operating System :: OS Independent
Classifier: Topic :: Scientific/Engineering :: Artificial Intelligence
Classifier: Topic :: Software Development :: Libraries :: Python Modules
Classifier: Intended Audience :: Education
Classifier: Intended Audience :: Science/Research
Classifier: Intended Audience :: Developers
Requires-Python: >=3.9
License-File: LICENSE
Requires-Dist: numpy
Requires-Dist: scipy
Requires-Dist: Blauwal3>=3.33.0
Provides-Extra: doc
Requires-Dist: sphinx; extra == "doc"
Requires-Dist: recommonmark; extra == "doc"
Requires-Dist: sphinx-rtd-theme; extra == "doc"
Provides-Extra: test
Requires-Dist: pytest; extra == "test"
Requires-Dist: coverage; extra == "test"
